fastq_dl/__init__.py
fastq_dl/cli/__init__.py
fastq_dl/cli/download.py
fastq_dl/constants.py
fastq_dl/providers/__init__.py
fastq_dl/providers/ena.py
fastq_dl/providers/generic.py
fastq_dl/providers/sra.py
fastq_dl/utils.py
fastq_dl-3.0.1.dist-info/LICENSE
fastq_dl-3.0.1.dist-info/WHEEL
fastq_dl-3.0.1.dist-info/entry_points.txt
fastq_dl-3.0.1.dist-info/METADATA
fastq_dl-3.0.1.dist-info/RECORD
