Metadata-Version: 2.1
Name: fastq-dl
Version: 3.0.1
Summary: Download FASTQ files from SRA or ENA repositories.
Home-page: https://github.com/rpetit3/fastq-dl
License: MIT
Keywords: bioinformatics,fastq,download,SRA,ENA
Author: Robert A. Petit III
Author-email: robbie.petit@gmail.com
Requires-Python: >=3.9,<3.13
Classifier: License :: OSI Approved :: MIT License
Classifier: Programming Language :: Python :: 3
Classifier: Programming Language :: Python :: 3.9
Classifier: Programming Language :: Python :: 3.10
Classifier: Programming Language :: Python :: 3.11
Requires-Dist: executor (>=23.2,<24.0)
Requires-Dist: markdown-it-py (==2.2.0)
Requires-Dist: pandas (>=2.2.3,<3.0.0)
Requires-Dist: pysradb (>=1.4,<2.0)
Requires-Dist: requests (>=2.31.0,<3.0.0)
Requires-Dist: rich (>=13.3.1,<14.0.0)
Requires-Dist: rich-click (>=1.6.1,<2.0.0)
Project-URL: Repository, https://github.com/rpetit3/fastq-dl
